ohnodb/__init__.py
ohnodb-1.0.1.dist-info/LICENSE
ohnodb-1.0.1.dist-info/WHEEL
ohnodb-1.0.1.dist-info/METADATA
ohnodb-1.0.1.dist-info/RECORD
