Metadata-Version: 2.1
Name: ohnodb
Version: 1.0.1
Summary: A very, very bad database
Home-page: https://github.com/vcokltfre/ohnodb
License: MIT
Author: vcokltfre
Author-email: vcokltfre@gmail.com
Requires-Python: >=3.8,<4.0
Classifier: License :: OSI Approved :: MIT License
Classifier: Programming Language :: Python :: 3
Classifier: Programming Language :: Python :: 3.8
Classifier: Programming Language :: Python :: 3.9
Requires-Dist: schema (>=0.7.4,<0.8.0)
Project-URL: Repository, https://github.com/vcokltfre/ohnodb
